Skyctl/__init__.py
Skyctl/terminal.py
skyctlzd-1.0.0.dist-info/METADATA
skyctlzd-1.0.0.dist-info/WHEEL
skyctlzd-1.0.0.dist-info/license.txt
skyctlzd-1.0.0.dist-info/top_level.txt
skyctlzd-1.0.0.dist-info/RECORD
