Metadata-Version: 2.1
Name: skyctlzd
Version: 1.0.0
Summary: 联云迁移工具
Author: xiejunwei
Author-email: xiejunwei@qq.com
License: MIT
Requires-Python: >=3
License-File: license.txt
Requires-Dist: pypinyin
Requires-Dist: opencv-python
